<?xml version="1.0" encoding="utf-8" ?><dwsync><file name="DJI_0089 Panorama BRANDED_00.jpg" server="home612542449.1and1-data.host" local="3578470442" remote="3578472300" Dst="-1" /><file name="DJI_0089 Panorama BRANDED_01.jpg" server="home612542449.1and1-data.host" local="3578470434" remote="3578472300" Dst="-1" /><file name="DJI_0089 Panorama BRANDED_03.jpg" server="home612542449.1and1-data.host" local="3578470434" remote="3578472300" Dst="-1" /><file name="DJI_0089 Panorama BRANDED_04.jpg" server="home612542449.1and1-data.host" local="3578470436" remote="3578472300" Dst="-1" /><file name="DJI_0089 Panorama BRANDED_02.jpg" server="home612542449.1and1-data.host" local="3578470434" remote="3578472300" Dst="-1" /><file name="DJI_0089 Panorama BRANDED_06.jpg" server="home612542449.1and1-data.host" local="3578470436" remote="3578472300" Dst="-1" /><file name="DJI_0089 Panorama BRANDED_05.jpg" server="home612542449.1and1-data.host" local="3578470436" remote="3578472300" Dst="-1" /><file name="DJI_0089 Panorama BRANDED_07.jpg" server="home612542449.1and1-data.host" local="3578470438" remote="3578472300" Dst="-1" /><file name="DJI_0089 Panorama BRANDED_08.jpg" server="home612542449.1and1-data.host" local="3578470438" remote="3578472300" Dst="-1" /><file name="DJI_0089 Panorama BRANDED_09.jpg" server="home612542449.1and1-data.host" local="3578470438" remote="3578472300" Dst="-1" /><file name="DJI_0089 Panorama BRANDED_10.jpg" server="home612542449.1and1-data.host" local="3578470440" remote="3578472300" Dst="-1" /><file name="DJI_0089 Panorama BRANDED_12.jpg" server="home612542449.1and1-data.host" local="3578470442" remote="3578472300" Dst="-1" /><file name="DJI_0089 Panorama BRANDED_11.jpg" server="home612542449.1and1-data.host" local="3578470440" remote="3578472300" Dst="-1" /><file name="DJI_0089 Panorama BRANDED_13.jpg" server="home612542449.1and1-data.host" local="3578470442" remote="3578472300" Dst="-1" /><file name="DJI_0089 Panorama BRANDED_14.jpg" server="home612542449.1and1-data.host" local="3578470442" remote="3578472300" Dst="-1" /><file name="index.htm" server="home612542449.1and1-data.host" local="3578472454" remote="3578472360" Dst="-1" /><file name="PTGuiViewer.js" server="home612542449.1and1-data.host" local="3578470432" remote="3578472300" Dst="-1" /><file name="PTGuiViewer.swf" server="home612542449.1and1-data.host" local="3578470432" remote="3578472300" Dst="-1" /><file name="DJI_0089 Panorama BRANDED.jpg" server="home612542449.1and1-data.host" local="3578466308" remote="3578472300" Dst="-1" /></dwsync>